tablestore/__init__.py
tablestore/aggregation.py
tablestore/auth.py
tablestore/client.py
tablestore/connection.py
tablestore/const_module.py
tablestore/consts.py
tablestore/credentials.py
tablestore/decoder.py
tablestore/encoder.py
tablestore/error.py
tablestore/flatbuffer/__init__.py
tablestore/flatbuffer/dataprotocol/BytesValue.py
tablestore/flatbuffer/dataprotocol/ColumnValues.py
tablestore/flatbuffer/dataprotocol/DataType.py
tablestore/flatbuffer/dataprotocol/RLEStringValues.py
tablestore/flatbuffer/dataprotocol/SQLResponseColumn.py
tablestore/flatbuffer/dataprotocol/SQLResponseColumns.py
tablestore/flatbuffer/dataprotocol/__init__.py
tablestore/flatbuffer/flat_buffer_decoder.py
tablestore/flatbuffer/sql.fbs
tablestore/flatbuffer/timeseries/BytesValue.py
tablestore/flatbuffer/timeseries/DataType.py
tablestore/flatbuffer/timeseries/FieldValues.py
tablestore/flatbuffer/timeseries/FlatBufferRowGroup.py
tablestore/flatbuffer/timeseries/FlatBufferRowInGroup.py
tablestore/flatbuffer/timeseries/FlatBufferRows.py
tablestore/flatbuffer/timeseries/Tag.py
tablestore/flatbuffer/timeseries/__init__.py
tablestore/flatbuffer/timeseries.fbs
tablestore/flatbuffer/timeseries_flat_buffer_encoder.py
tablestore/group_by.py
tablestore/metadata.py
tablestore/native/README.md
tablestore/native/__init__.py
tablestore/native/native_plainbuffer.c
tablestore/native/native_plainbuffer.cpython-313-darwin.so
tablestore/native/native_plainbuffer.so
tablestore/plainbuffer/__init__.py
tablestore/plainbuffer/plain_buffer_builder.py
tablestore/plainbuffer/plain_buffer_coded_stream.py
tablestore/plainbuffer/plain_buffer_consts.py
tablestore/plainbuffer/plain_buffer_crc8.py
tablestore/plainbuffer/plain_buffer_stream.py
tablestore/protobuf/__init__.py
tablestore/protobuf/search.proto
tablestore/protobuf/search_pb2.py
tablestore/protobuf/table_store.proto
tablestore/protobuf/table_store_filter.proto
tablestore/protobuf/table_store_filter_pb2.py
tablestore/protobuf/table_store_pb2.py
tablestore-6.3.8.dist-info/METADATA
tablestore-6.3.8.dist-info/WHEEL
tablestore-6.3.8.dist-info/licenses/LICENSE
tablestore-6.3.8.dist-info/RECORD
