Metadata-Version: 2.4
Name: tablestore
Version: 6.3.8
Summary: Aliyun TableStore(OTS) SDK
License: Apache-2.0
License-File: LICENSE
Author: xunjian.sl
Author-email: xunjian.sl@alibaba-inc.com
Requires-Python: >=3.8,<4.0
Classifier: License :: OSI Approved :: Apache Software License
Classifier: Programming Language :: Python :: 3
Classifier: Programming Language :: Python :: 3.8
Classifier: Programming Language :: Python :: 3.9
Classifier: Programming Language :: Python :: 3.10
Classifier: Programming Language :: Python :: 3.11
Classifier: Programming Language :: Python :: 3.12
Classifier: Programming Language :: Python :: 3.13
Classifier: Programming Language :: Python :: 3.14
Requires-Dist: aiohttp (>=3.8)
Requires-Dist: certifi (>=2016.2.28)
Requires-Dist: crc32c (>=2.7.1)
Requires-Dist: flatbuffers (>=22.9.24)
Requires-Dist: future (>=0.16.0)
Requires-Dist: numpy (>=1.11.0)
Requires-Dist: protobuf (>=3.20.0,<6.0.0)
Requires-Dist: six (>=1.11.0)
Requires-Dist: urllib3 (>=1.14)
Project-URL: Homepage, https://www.aliyun.com/product/ots
